pya3/__init__.py
pya3/alicebluepy.py
pya3-1.0.30.dist-info/METADATA
pya3-1.0.30.dist-info/WHEEL
pya3-1.0.30.dist-info/top_level.txt
pya3-1.0.30.dist-info/RECORD
