Metadata-Version: 2.1
Name: pya3
Version: 1.0.30
Summary: Official Python SDK for Alice Blue API
Home-page: https://a3.aliceblueonline.com/
Author: Codifi
Author-email: pradeep@codifi.in
License: MIT
Platform: UNKNOWN
Classifier: Programming Language :: Python :: 3.9
Classifier: License :: OSI Approved :: MIT License
Classifier: Operating System :: OS Independent
Classifier: Natural Language :: English
Classifier: Intended Audience :: Developers
Requires-Python: >=3.7
